{
  "metadata": {
    "generated_at": "2025-12-03 08:47 PM IST",
    "total_models": 3,
    "pipeline_stage": "L_collate_custom_licenses"
  },
  "models": [
    {
      "id": "nvidia/nemotron-nano-12b-v2-vl:free",
      "canonical_slug": "nvidia/nemotron-nano-12b-v2-vl",
      "original_name": "NVIDIA: Nemotron Nano 12B 2 VL (free)",
      "hugging_face_id": "nvidia/NVIDIA-Nemotron-Nano-12B-v2-VL-BF16",
      "clean_model_name": "Nemotron Nano 12B 2 VL",
      "license_info_text": "",
      "license_info_url": "",
      "license_name": "NVIDIA",
      "license_url": "https://huggingface.co/nvidia/NVIDIA-Nemotron-Nano-12B-v2-VL-BF16/blob/main/README.md"
    },
    {
      "id": "nvidia/nemotron-nano-9b-v2:free",
      "canonical_slug": "nvidia/nemotron-nano-9b-v2",
      "original_name": "NVIDIA: Nemotron Nano 9B V2 (free)",
      "hugging_face_id": "nvidia/NVIDIA-Nemotron-Nano-9B-v2",
      "clean_model_name": "Nemotron Nano 9B V2",
      "license_info_text": "",
      "license_info_url": "",
      "license_name": "NVIDIA",
      "license_url": "https://huggingface.co/nvidia/NVIDIA-Nemotron-Nano-9B-v2/blob/main/README.md"
    },
    {
      "id": "moonshotai/kimi-k2:free",
      "canonical_slug": "moonshotai/kimi-k2",
      "original_name": "MoonshotAI: Kimi K2 0711 (free)",
      "hugging_face_id": "moonshotai/Kimi-K2-Instruct",
      "clean_model_name": "Kimi K2 0711",
      "license_info_text": "",
      "license_info_url": "",
      "license_name": "Modified MIT",
      "license_url": "https://huggingface.co/moonshotai/Kimi-K2-Instruct/blob/main/LICENSE"
    }
  ]
}